appium_flutter_report/__init__.py
appium_flutter_report/group_and_test.py
appium_flutter_report/logger.py
appium_flutter_report/report_generator.py
appium_flutter_report/test_case.py
appium_flutter_report-0.1.6.dist-info/METADATA
appium_flutter_report-0.1.6.dist-info/WHEEL
appium_flutter_report-0.1.6.dist-info/licenses/LICENSE
appium_flutter_report-0.1.6.dist-info/RECORD
