Metadata-Version: 2.1
Name: appium_flutter_report
Version: 0.1.6
Summary: A package for generating Appium Flutter Report.
Project-URL: Homepage, https://github.com/AradhyaNepal/AppiumFlutterReport/tree/main/PythonReportGenerator
Project-URL: Bug Tracker, https://github.com/AradhyaNepal/AppiumFlutterReport/issues
Author-email: Aaradhya Gopal Nepal <aradhya.1441@gmail.com>
License-File: LICENSE
Classifier: License :: OSI Approved :: MIT License
Classifier: Operating System :: OS Independent
Classifier: Programming Language :: Python :: 3
Requires-Python: >=3.7
